example_app/__init__.py
example_app/example.py
antonio_example_app_kc-0.0.22.dist-info/METADATA
antonio_example_app_kc-0.0.22.dist-info/WHEEL
antonio_example_app_kc-0.0.22.dist-info/top_level.txt
antonio_example_app_kc-0.0.22.dist-info/RECORD
